open_weather_api/__init__.py
open_weather_api/api_helper.py
open_weather_api/configuration.py
open_weather_api/decorators.py
open_weather_api/open_weather_api_client.py
open_weather_api/controllers/__init__.py
open_weather_api/controllers/base_controller.py
open_weather_api/controllers/weather_ap_is_controller.py
open_weather_api/exceptions/__init__.py
open_weather_api/exceptions/api_exception.py
open_weather_api/http/__init__.py
open_weather_api/http/http_call_back.py
open_weather_api/http/http_client.py
open_weather_api/http/http_context.py
open_weather_api/http/http_method_enum.py
open_weather_api/http/http_request.py
open_weather_api/http/http_response.py
open_weather_api/http/requests_client.py
open_weather_api/http/auth/__init__.py
open_weather_api/http/auth/custom_query_auth.py
open_weather_api/models/__init__.py
open_weather_api/models/clouds.py
open_weather_api/models/coord.py
open_weather_api/models/lang_enum.py
open_weather_api/models/main.py
open_weather_api/models/mode_enum.py
open_weather_api/models/sys.py
open_weather_api/models/units_enum.py
open_weather_api/models/weather.py
open_weather_api/models/weather_api_response.py
open_weather_api/models/wind.py
Open_Weather_API-1.0.dist-info/LICENSE
Open_Weather_API-1.0.dist-info/METADATA
Open_Weather_API-1.0.dist-info/WHEEL
Open_Weather_API-1.0.dist-info/top_level.txt
Open_Weather_API-1.0.dist-info/RECORD
